rocktalk/__init__.py
rocktalk/__main__.py
rocktalk/app.py
rocktalk/app_context.py
rocktalk/components/__init__.py
rocktalk/components/base.py
rocktalk/components/sidebar.py
rocktalk/components/chat/__init__.py
rocktalk/components/chat/chat_interface.py
rocktalk/components/chat/message_display.py
rocktalk/components/chat/response_generator.py
rocktalk/components/chat/user_input.py
rocktalk/components/dialogs/__init__.py
rocktalk/components/dialogs/general_options.py
rocktalk/components/dialogs/save_temporary_session.py
rocktalk/components/dialogs/search.py
rocktalk/components/dialogs/session_settings.py
rocktalk/components/dialogs/template_selector.py
rocktalk/config/__init__.py
rocktalk/config/button_group.py
rocktalk/config/parameter_controls.py
rocktalk/config/settings.py
rocktalk/models/__init__.py
rocktalk/models/interfaces.py
rocktalk/models/llm.py
rocktalk/models/rate_limiter.py
rocktalk/models/storage/__init__.py
rocktalk/models/storage/sqlite.py
rocktalk/models/storage/storage_interface.py
rocktalk/services/bedrock.py
rocktalk/services/creds.py
rocktalk/utils/__init__.py
rocktalk/utils/date_utils.py
rocktalk/utils/datetime_utils.py
rocktalk/utils/image_utils.py
rocktalk/utils/js.py
rocktalk/utils/log.py
rocktalk/utils/streamlit_utils.py
rocktalk-0.6.0.dist-info/licenses/LICENSE
rocktalk-0.6.0.dist-info/METADATA
rocktalk-0.6.0.dist-info/WHEEL
rocktalk-0.6.0.dist-info/entry_points.txt
rocktalk-0.6.0.dist-info/top_level.txt
rocktalk-0.6.0.dist-info/RECORD
