Metadata-Version: 2.4
Name: rocktalk
Version: 0.6.0
Summary: A private and locally running ChatBot WebApp with Streamlit, LangChain, and Amazon Bedrock
Author-email: Tyler House <26489166+tahouse@users.noreply.github.com>
License: Apache-2.0
Project-URL: Homepage, https://github.com/tahouse/rocktalk
Project-URL: Documentation, https://github.com/tahouse/rocktalk/blob/main/README.md
Project-URL: Issue Tracker, https://github.com/tahouse/rocktalk/issues
Project-URL: Repository, https://github.com/tahouse/rocktalk
Keywords: streamlit,chatbot,langchain,amazon-bedrock,bedrock,ai-chat,llm,chat-interface,aws,conversational-ai,gen-ai
Classifier: Programming Language :: Python :: 3.11
Classifier: Programming Language :: Python :: 3.12
Classifier: Programming Language :: Python :: 3.13
Classifier: License :: OSI Approved :: Apache Software License
Classifier: Operating System :: OS Independent
Classifier: Development Status :: 4 - Beta
Classifier: Environment :: Web Environment
Classifier: Intended Audience :: Developers
Classifier: Topic :: Internet :: WWW/HTTP :: Dynamic Content
Classifier: Topic :: Scientific/Engineering :: Artificial Intelligence
Classifier: Topic :: Software Development :: Libraries :: Python Modules
Requires-Python: >=3.11
License-File: LICENSE
Requires-Dist: langchain>=0.3.4
Requires-Dist: langchain-aws>=0.2.21
Requires-Dist: boto3>=1.35.44
Requires-Dist: python-dotenv>=1.0.1
Requires-Dist: pydantic>=2.9.2
Requires-Dist: pandas>=2.2.3
Requires-Dist: streamlit==1.43.2
Requires-Dist: streamlit-keywords>=0.1.12
Requires-Dist: streamlit-authenticator>=0.4.1
Requires-Dist: streamlit-chat-prompt>=0.4.1
Requires-Dist: streamlit-js-eval>=0.1.7
Requires-Dist: streamlit-javascript==0.1.5
Requires-Dist: streamlit-shortcuts>=0.1.9
Requires-Dist: streamlit_float>=0.3.5
Requires-Dist: st-theme>=1.2.3
Requires-Dist: typing_extensions>=4.12.2
Requires-Dist: boto3-stubs[bedrock]==1.36.0
Provides-Extra: dev
Requires-Dist: pytest>=7.4.2; extra == "dev"
Requires-Dist: black>=25.1.0; extra == "dev"
Requires-Dist: flake8>=7.1.1; extra == "dev"
Requires-Dist: mypy>=1.7.0; extra == "dev"
Requires-Dist: pre-commit>=4.1.0; extra == "dev"
Requires-Dist: autoflake>=3.2.0; extra == "dev"
Dynamic: license-file
